{
  "_comment": "VS Code GitHub Copilot MCP Configuration for AndroJack",
  "_instructions": [
    "VS Code supports MCP via .vscode/mcp.json (workspace) or User settings.",
    "",
    "OPTION A – Workspace (recommended — check into your Android repo):",
    "  Create: <your-android-project>/.vscode/mcp.json",
    "  Content: the 'servers' object below.",
    "",
    "OPTION B – User settings.json:",
    "  Add inside your existing settings.json:",
    "  'github.copilot.mcp.servers': { ... servers object ... }",
    "",
    "After saving, open GitHub Copilot Chat → Agent mode → '+' → you should see AndroJack tools.",
    "VS Code version 1.99+ required for MCP support."
  ],
  "servers": {
    "androjack": {
      "type": "stdio",
      "command": "npx",
      "args": ["-y", "androjack-mcp@1.6.4"]
    }
  }
}
